[{"type":"icon","data":{"key":"Wonderland","point":{"x":-9074544,"z":-6254641},"image":"pin","size":{"x":20.0,"z":20.0},"anchor":{"x":4.5,"z":17.0}},"options":{"stroke":{"weight":5,"color":-13095215},"tooltip":{"content":"Canada's Wonderland","direction":2,"sticky":true},"popup":{"content":"<html><style>@font-face {font-family: avenir;src: url('fonts/Avenir Regular/Avenir Regular.ttf');}@font-face {font-family: avenir_bold;src: url('fonts/Avenir Heavy/Avenir Heavy.ttf');}.description_container {display: grid;grid-template-columns: auto auto;gap: 10px;padding: 10px;width: 280px;background-image: url('images/Wood.png');background-size: 50px;font-family: avenir;}.img_small {position: relative;height: 75px;}.img_small:hover {transform: scale(1.5);z-index: 1000;}.img_small img {height: 100%;width: 100%;object-fit: cover;}.img_large {position: relative;grid-column: 1 / span 2;height: 150px;object-fit: cover;}.img_large:hover {transform: scale(1.5);z-index: 1000;}.img_large img {height: 100%;width: 100%;object-fit: cover;}.text {grid-column: 1 / span 2;padding: 10px;border-radius: 25px;background-image: url('images/Stone_Bricks.png');background-size: 50px;color: black;}.image_top_text {position: absolute;bottom: -5px;left: 10px;color: snow;font-size: 1.8rem;}.image_bottom_text {position: absolute;bottom: 1px;left: 3px;color: snow;}h1 {font-family: avenir_bold;margin: 0px auto;}.flags {display: flex;position: absolute;top: 5px;left: 3px;padding: 10px;gap: 10px;}.flags img {height: 20px;object-fit: cover;}.warp_text {color: orange;cursor: pointer;position: relative;white-space: nowrap;}.warp_text:hover {color: aqua;text-decoration: underline;}.warp_text .copy_warp {visibility: hidden;width: 120px;background-color: #555;color: #fff;text-align: center;border-radius: 6px;padding: 5px 0;position: absolute;z-index: 1;bottom: 125%;left: 50%;margin-left: -60px;opacity: 0;transition: opacity 0.3s;}.tooltip .tooltiptext::after {content: '';position: absolute;top: 100%;left: 50%;margin-left: -5px;border-width: 5px;border-style: solid;border-color: #555 transparent transparent transparent;}.warp_text:hover .copy_warp {visibility: visible;opacity: 1;}</style><body><div class='description_container'><div class='img_large'><img src='images/ON/Wonderland1.png' alt='img1' /><div class='flags'><img src='images/ON/ON.png' alt='flag 1'/></div><div class='image_top_text'><h3></h3></div></div><div class='text'><h1>Canada's Wonderland, ON</h1><p style='color: snow; margin-top: 0px;'>Canada's Wonderland is the largest and most visited amusement park in Canada. As of 2025, it operates over 200 attractions, 60 thrill rides and 18 roller coasters. 3,800,000 thrill seekers visit every year. Will you be one of them?</p><p>You can visit here by using <span class='warp_text' onclick='navigator.clipboard.writeText(this.childNodes[0].textContent)'> /warp Canada'sWonderland<span class='copy_warp'>Click to copy me</span></span> on the server.</p></div><div class='img_small'><img src='images/ON/Wonderland2.png' alt='img2'/><div class='image_bottom_text'></div></div><div class='img_small'><img src='images/ON/Wonderland3.png' alt='img3'/><div class='image_bottom_text'></div></div></div></body></html>","offset":{"x":2,"z":-8}}}},{"type":"icon","data":{"key":"Vancouver","point":{"x":-12402926,"z":-7108418},"image":"pin","size":{"x":20.0,"z":20.0},"anchor":{"x":8.0,"z":17.0}},"options":{"stroke":{"weight":5,"color":-13095215},"tooltip":{"content":"Vancouver","direction":2,"sticky":true},"popup":{"content":"<html><style>@font-face {font-family: avenir;src: url('fonts/Avenir Regular/Avenir Regular.ttf');}@font-face {font-family: avenir_bold;src: url('fonts/Avenir Heavy/Avenir Heavy.ttf');}.description_container {display: grid;grid-template-columns: auto auto;gap: 10px;padding: 10px;width: 280px;background-image: url('images/Wood.png');background-size: 50px;font-family: avenir;}.img_small {position: relative;height: 75px;}.img_small:hover {transform: scale(1.5);z-index: 1000;}.img_small img {height: 100%;width: 100%;object-fit: cover;}.img_large {position: relative;grid-column: 1 / span 2;height: 150px;object-fit: cover;}.img_large:hover {transform: scale(1.5);z-index: 1000;}.img_large img {height: 100%;width: 100%;object-fit: cover;}.text {grid-column: 1 / span 2;padding: 10px;border-radius: 25px;background-image: url('images/Stone_Bricks.png');background-size: 50px;color: black;}.image_top_text {position: absolute;bottom: -5px;left: 10px;color: snow;font-size: 1.8rem;}.image_bottom_text {position: absolute;bottom: 1px;left: 3px;color: snow;}h1 {font-family: avenir_bold;margin: 0px auto;}.flags {display: flex;position: absolute;top: 5px;left: 3px;padding: 10px;gap: 10px;}.flags img {height: 20px;object-fit: cover;}.warp_text {color: orange;cursor: pointer;position: relative;white-space: nowrap;}.warp_text:hover {color: aqua;text-decoration: underline;}.warp_text .copy_warp {visibility: hidden;width: 120px;background-color: #555;color: #fff;text-align: center;border-radius: 6px;padding: 5px 0;position: absolute;z-index: 1;bottom: 125%;left: 50%;margin-left: -60px;opacity: 0;transition: opacity 0.3s;}.tooltip .tooltiptext::after {content: '';position: absolute;top: 100%;left: 50%;margin-left: -5px;border-width: 5px;border-style: solid;border-color: #555 transparent transparent transparent;}.warp_text:hover .copy_warp {visibility: visible;opacity: 1;}</style><body><div class='description_container'><div class='img_large'><img src='images/BC/Vancouver1.png' alt='img1' /><div class='flags'><img src='images/BC/BC.png' alt='flag 1'/><img src='images/BC/Vancouver_Flag.png' alt='flag 2'/></div><div class='image_top_text'><h3></h3></div></div><div class='text'><h1>Vancouver, BC</h1><p style='color: snow; margin-top: 0px;'>Vancouver is the largest city in British Columbia. A bustling metroplis, it has hosted many international events such as the Olympics, TedX talks and green peace. Additionally, it is also a popular filming location for movie studios.</p><p>You can visit here by using <span class='warp_text' onclick='navigator.clipboard.writeText(this.childNodes[0].textContent)'>/warp Vancouver_BC<span class='copy_warp'>Click to copy me</span></span> on the server.</p></div><div class='img_small'><img src='images/BC/Vancouver2.png' alt='img2'/><div class='image_bottom_text'></div></div><div class='img_small'><img src='images/BC/Vancouver3.png' alt='img3'/><div class='image_bottom_text'></div></div></div></body></html>","offset":{"x":2,"z":-8}}}},{"type":"icon","data":{"key":"Charlottetown","point":{"x":-7915557,"z":-6952114},"image":"POI","size":{"x":20.0,"z":20.0},"anchor":{"x":4.5,"z":17.0}},"options":{"stroke":{"weight":5,"color":-13095215},"tooltip":{"content":"Charlottetown","direction":2,"sticky":true},"popup":{"content":"<!--Use this tool to compress the HTML: https://www.textfixer.com/html/compress-html-compression.php --><html><style>@font-face {font-family: avenir;src: url('fonts/Avenir Regular/Avenir Regular.ttf');}@font-face {font-family: avenir_bold;src: url('fonts/Avenir Heavy/Avenir Heavy.ttf');}.description_container {display: grid;grid-template-columns: auto auto;gap: 10px;padding: 10px;width: 280px;background-image: url('images/Wood.png');background-size: 50px;font-family: avenir;}.img_small {position: relative;height: 75px;}.img_small:hover {transform: scale(1.5);z-index: 1000;}.img_small img {height: 100%;width: 100%;object-fit: cover;}.img_large {position: relative;grid-column: 1 / span 2;height: 150px;object-fit: cover;}.img_large:hover {transform: scale(1.5);z-index: 1000;}.img_large img {height: 100%;width: 100%;object-fit: cover;}.text {grid-column: 1 / span 2;padding: 10px;border-radius: 25px;background-image: url('images/Stone_Bricks.png');background-size: 50px;color: black;}.image_top_text {position: absolute;bottom: -5px;left: 10px;color: snow;font-size: 1.8rem;}.image_bottom_text {position: absolute;bottom: 1px;left: 3px;color: snow;}h1 {font-family: avenir_bold;margin: 0px auto;}.flags {display: flex;position: absolute;top: 5px;left: 3px;padding: 10px;gap: 10px;}.flags img {height: 20px;object-fit: cover;}.warp_text {color: orange;cursor: pointer;position: relative;white-space: nowrap;}.warp_text:hover {color: aqua;text-decoration: underline;}.warp_text .copy_warp {visibility: hidden;width: 120px;background-color: #555;color: #fff;text-align: center;border-radius: 6px;padding: 5px 0;position: absolute;z-index: 1;bottom: 125%;left: 50%;margin-left: -60px;opacity: 0;transition: opacity 0.3s;}.tooltip .tooltiptext::after {content: '';position: absolute;top: 100%;left: 50%;margin-left: -5px;border-width: 5px;border-style: solid;border-color: #555 transparent transparent transparent;}.warp_text:hover .copy_warp {visibility: visible;opacity: 1;}</style><body><div class='description_container'><div class='img_large'><img src='images/PEI/Charlotte1.png' alt='img1' /><div class='flags'><img src='images/PEI/PEI.png' alt='flag 1'/><img src='images/PEI/Charlotte_Flag.png' alt='flag 2'/></div><div class='image_top_text'><h3></h3></div></div><div class='text'><h1>Charlottetown, PEI</h1><p style='color: snow; margin-top: 0px;'>Charlottetown is the capital of Prince Edward Island. Known for it's large potato production, it grows 25% of all Canadian potatoes despite the small size of the province. Confederation bridge, the worlds longest bridge to cross ice covered water, connects the island to the mainland. Within Charlottetown sits <i>Province House</i>, where the Canadian confederation was first discussed. </p><p>You can visit here by using <span class='warp_text' onclick='navigator.clipboard.writeText(this.childNodes[0].textContent)'> /warp Charlottetown<span class='copy_warp'>Click to copy me</span></span> on the server.</p></div><div class='img_small'><img src='images/PEI/Charlotte2.png' alt='img2'/><div class='image_bottom_text'></div></div><div class='img_small'><img src='images/PEI/Charlotte3.png' alt='img3'/><div class='image_bottom_text'></div></div></div></body></html>","offset":{"x":2,"z":-6}}}},{"type":"icon","data":{"key":"Whitehorse","point":{"x":-12446052,"z":-8766898},"image":"POI","size":{"x":20.0,"z":20.0},"anchor":{"x":4.5,"z":17.0}},"options":{"stroke":{"weight":5,"color":-13095215},"tooltip":{"content":"Whitehorse","direction":2,"sticky":true},"popup":{"content":"<html><style>@font-face {font-family: avenir;src: url('fonts/Avenir Regular/Avenir Regular.ttf');}@font-face {font-family: avenir_bold;src: url('fonts/Avenir Heavy/Avenir Heavy.ttf');}.description_container {display: grid;grid-template-columns: auto auto;gap: 10px;padding: 10px;width: 280px;background-image: url('images/Wood.png');background-size: 50px;font-family: avenir;}.img_small {position: relative;height: 75px;}.img_small:hover {transform: scale(1.5);z-index: 1000;}.img_small img {height: 100%;width: 100%;object-fit: cover;}.img_large {position: relative;grid-column: 1 / span 2;height: 150px;object-fit: cover;}.img_large:hover {transform: scale(1.5);z-index: 1000;}.img_large img {height: 100%;width: 100%;object-fit: cover;}.text {grid-column: 1 / span 2;padding: 10px;border-radius: 25px;background-image: url('images/Stone_Bricks.png');background-size: 50px;color: black;}.image_top_text {position: absolute;bottom: -5px;left: 10px;color: snow;font-size: 1.8rem;}.image_bottom_text {position: absolute;bottom: 1px;left: 3px;color: snow;}h1 {font-family: avenir_bold;margin: 0px auto;}.flags {display: flex;position: absolute;top: 5px;left: 3px;padding: 10px;gap: 10px;}.flags img {height: 20px;object-fit: cover;}.warp_text {color: orange;cursor: pointer;position: relative;white-space: nowrap;}.warp_text:hover {color: aqua;text-decoration: underline;}.warp_text .copy_warp {visibility: hidden;width: 120px;background-color: #555;color: #fff;text-align: center;border-radius: 6px;padding: 5px 0;position: absolute;z-index: 1;bottom: 125%;left: 50%;margin-left: -60px;opacity: 0;transition: opacity 0.3s;}.tooltip .tooltiptext::after {content: '';position: absolute;top: 100%;left: 50%;margin-left: -5px;border-width: 5px;border-style: solid;border-color: #555 transparent transparent transparent;}.warp_text:hover .copy_warp {visibility: visible;opacity: 1;}</style><body><div class='description_container'><div class='img_large'><img src='images/YT/Whitehorse1.png' alt='img1' /><div class='flags'><img src='images/YT/YT.png' alt='flag 1'/><img src='images/YT/Whitehorse_Flag.png' alt='flag 2'/></div><div class='image_top_text'><h3></h3></div></div><div class='text'><h1>Whitehorse, YT</h1><p style='color: snow; margin-top: 0px;'>Whitehorse is the capital of Yukon and title holder of the least air polluted city in the world. The city sits at kilometer 1,425 of the Alaska Highway. Historically, it experienced a gold rush in the nearby Klondike region between 1896 and 1899. Buildings are often constructed from or around old military lodgings and neighborhoods are often separated by major geological features due to the varied topography.</p><p>You can visit here by using <span class='warp_text' onclick='navigator.clipboard.writeText(this.childNodes[0].textContent)'>/warp Whitehorse<span class='copy_warp'>Click to copy me</span></span> on the server.</p></div><div class='img_small'><img src='images/YT/Whitehorse2.png' alt='img2'/><div class='image_bottom_text'></div></div><div class='img_small'><img src='images/YT/Whitehorse3.png' alt='img3'/><div class='image_bottom_text'></div></div></div></body></html>"}}},{"type":"icon","data":{"key":"Yellowknife","point":{"x":-11321412,"z":-8382383},"image":"POI","size":{"x":20.0,"z":20.0},"anchor":{"x":4.5,"z":17.0}},"options":{"stroke":{"weight":5,"color":-13095215},"tooltip":{"content":"Yellowknife","direction":2,"sticky":true},"popup":{"content":"<html><style>@font-face {font-family: avenir;src: url('fonts/Avenir Regular/Avenir Regular.ttf');}@font-face {font-family: avenir_bold;src: url('fonts/Avenir Heavy/Avenir Heavy.ttf');}.description_container {display: grid;grid-template-columns: auto auto;gap: 10px;padding: 10px;width: 280px;background-image: url('images/Wood.png');background-size: 50px;font-family: avenir;}.img_small {position: relative;height: 75px;}.img_small:hover {transform: scale(1.5);z-index: 1000;}.img_small img {height: 100%;width: 100%;object-fit: cover;}.img_large {position: relative;grid-column: 1 / span 2;height: 150px;object-fit: cover;}.img_large:hover {transform: scale(1.5);z-index: 1000;}.img_large img {height: 100%;width: 100%;object-fit: cover;}.text {grid-column: 1 / span 2;padding: 10px;border-radius: 25px;background-image: url('images/Stone_Bricks.png');background-size: 50px;color: black;}.image_top_text {position: absolute;bottom: -5px;left: 10px;color: snow;font-size: 1.8rem;}.image_bottom_text {position: absolute;bottom: 1px;left: 3px;color: snow;}h1 {font-family: avenir_bold;margin: 0px auto;}.flags {display: flex;position: absolute;top: 5px;left: 3px;padding: 10px;gap: 10px;}.flags img {height: 20px;object-fit: cover;}.warp_text {color: orange;cursor: pointer;position: relative;white-space: nowrap;}.warp_text:hover {color: aqua;text-decoration: underline;}.warp_text .copy_warp {visibility: hidden;width: 120px;background-color: #555;color: #fff;text-align: center;border-radius: 6px;padding: 5px 0;position: absolute;z-index: 1;bottom: 125%;left: 50%;margin-left: -60px;opacity: 0;transition: opacity 0.3s;}.tooltip .tooltiptext::after {content: '';position: absolute;top: 100%;left: 50%;margin-left: -5px;border-width: 5px;border-style: solid;border-color: #555 transparent transparent transparent;}.warp_text:hover .copy_warp {visibility: visible;opacity: 1;}</style><body><div class='description_container'><div class='img_large'><img src='images/NWT/Yellowknife1.png' alt='img1' /><div class='flags'><img src='images/NWT/NWT.png' alt='flag 1'/><img src='images/NWT/Yellowknife_Flag.png' alt='flag 2'/></div><div class='image_top_text'><h3></h3></div></div><div class='text'><h1>Yellowknife, NWT</h1><p style='color: snow; margin-top: 0px;'>Yellowknife is the capital and only city of the Northwest Territories. Nowadays, it is mainly known for its diamond mining industry and arctic tourism. Attractions include the Gold Range Bar (one of Canada's oldest drinking establishments) and one of the oldest Hudson's Bay Warehouses, which supplied materials to northern gold prospectors.</p><p>You can visit here by using <span class='warp_text' onclick='navigator.clipboard.writeText(this.childNodes[0].textContent)'>/warp Yellowknife<span class='copy_warp'>Click to copy me</span></span> on the server.</p></div><div class='img_small'><img src='images/NWT/Yellowknife2.png' alt='img2'/><div class='image_bottom_text'></div></div><div class='img_small'><img src='images/NWT/Yellowknife3.png' alt='img3'/><div class='image_bottom_text'></div></div></div></body></html>"}}},{"type":"icon","data":{"key":"Regina","point":{"x":-11018985,"z":-6906705},"image":"POI","size":{"x":20.0,"z":20.0},"anchor":{"x":4.5,"z":17.0}},"options":{"stroke":{"weight":5,"color":-13095215},"tooltip":{"content":"Regina","direction":2,"sticky":true},"popup":{"content":"<html><style>@font-face {font-family: avenir;src: url('fonts/Avenir Regular/Avenir Regular.ttf');}@font-face {font-family: avenir_bold;src: url('fonts/Avenir Heavy/Avenir Heavy.ttf');}.description_container {display: grid;grid-template-columns: auto auto;gap: 10px;padding: 10px;width: 280px;background-image: url('images/Wood.png');background-size: 50px;font-family: avenir;}.img_small {position: relative;height: 75px;}.img_small:hover {transform: scale(1.5);z-index: 1000;}.img_small img {height: 100%;width: 100%;object-fit: cover;}.img_large {position: relative;grid-column: 1 / span 2;height: 150px;object-fit: cover;}.img_large:hover {transform: scale(1.5);z-index: 1000;}.img_large img {height: 100%;width: 100%;object-fit: cover;}.text {grid-column: 1 / span 2;padding: 10px;border-radius: 25px;background-image: url('images/Stone_Bricks.png');background-size: 50px;color: black;}.image_top_text {position: absolute;bottom: -5px;left: 10px;color: snow;font-size: 1.8rem;}.image_bottom_text {position: absolute;bottom: 1px;left: 3px;color: snow;}h1 {font-family: avenir_bold;margin: 0px auto;}.flags {display: flex;position: absolute;top: 5px;left: 3px;padding: 10px;gap: 10px;}.flags img {height: 20px;object-fit: cover;}.warp_text {color: orange;cursor: pointer;position: relative;white-space: nowrap;}.warp_text:hover {color: aqua;text-decoration: underline;}.warp_text .copy_warp {visibility: hidden;width: 120px;background-color: #555;color: #fff;text-align: center;border-radius: 6px;padding: 5px 0;position: absolute;z-index: 1;bottom: 125%;left: 50%;margin-left: -60px;opacity: 0;transition: opacity 0.3s;}.tooltip .tooltiptext::after {content: '';position: absolute;top: 100%;left: 50%;margin-left: -5px;border-width: 5px;border-style: solid;border-color: #555 transparent transparent transparent;}.warp_text:hover .copy_warp {visibility: visible;opacity: 1;}</style><body><div class='description_container'><div class='img_large'><img src='images/SK/Regina1.png' alt='img1' /><div class='flags'><img src='images/SK/SK.png' alt='flag 1'/><img src='images/SK/Regina_Flag.png' alt='flag 2'/></div><div class='image_top_text'><h3>Cenotaph</h3></div></div><div class='text'><h1>Regina, SK</h1><p style='color: snow; margin-top: 0px;'>Regina is the capital of Saskatchewan. A major exporter of potash and wheat, it is surrounded by generational farmland. Attractions include the Royal Saskatchewan Museum, Hotel Saskatchewan and the RCMP's national training centre.</p><p>You can visit here by using <span class='warp_text' onclick='navigator.clipboard.writeText(this.childNodes[0].textContent)'>/warp Regina<span class='copy_warp'>Click to copy me</span></span> on the server.</p></div><div class='img_small'><img src='images/SK/Regina2.png' alt='img2'/><div class='image_bottom_text'>Regina Airport</div></div><div class='img_small'><img src='images/SK/Regina3.png' alt='img3'/><div class='image_bottom_text'></div></div></div></body></html>"}}},{"type":"icon","data":{"key":"Calgary","point":{"x":-11681074,"z":-7012448},"image":"pin","size":{"x":20.0,"z":20.0},"anchor":{"x":4.5,"z":17.0}},"options":{"stroke":{"weight":5,"color":-13095215},"tooltip":{"content":"Calgary","direction":2,"sticky":true},"popup":{"content":"<html><style>@font-face {font-family: avenir;src: url('fonts/Avenir Regular/Avenir Regular.ttf');}@font-face {font-family: avenir_bold;src: url('fonts/Avenir Heavy/Avenir Heavy.ttf');}.description_container {display: grid;grid-template-columns: auto auto;gap: 10px;padding: 10px;width: 280px;background-image: url('images/Wood.png');background-size: 50px;font-family: avenir;}.img_small {position: relative;height: 75px;}.img_small:hover {transform: scale(1.5);z-index: 1000;}.img_small img {height: 100%;width: 100%;object-fit: cover;}.img_large {position: relative;grid-column: 1 / span 2;height: 150px;object-fit: cover;}.img_large:hover {transform: scale(1.5);z-index: 1000;}.img_large img {height: 100%;width: 100%;object-fit: cover;}.text {grid-column: 1 / span 2;padding: 10px;border-radius: 25px;background-image: url('images/Stone_Bricks.png');background-size: 50px;color: black;}.image_top_text {position: absolute;bottom: -5px;left: 10px;color: snow;font-size: 1.8rem;}.image_bottom_text {position: absolute;bottom: 1px;left: 3px;color: snow;}h1 {font-family: avenir_bold;margin: 0px auto;}.flags {display: flex;position: absolute;top: 5px;left: 3px;padding: 10px;gap: 10px;}.flags img {height: 20px;object-fit: cover;}.warp_text {color: orange;cursor: pointer;position: relative;white-space: nowrap;}.warp_text:hover {color: aqua;text-decoration: underline;}.warp_text .copy_warp {visibility: hidden;width: 120px;background-color: #555;color: #fff;text-align: center;border-radius: 6px;padding: 5px 0;position: absolute;z-index: 1;bottom: 125%;left: 50%;margin-left: -60px;opacity: 0;transition: opacity 0.3s;}.tooltip .tooltiptext::after {content: '';position: absolute;top: 100%;left: 50%;margin-left: -5px;border-width: 5px;border-style: solid;border-color: #555 transparent transparent transparent;}.warp_text:hover .copy_warp {visibility: visible;opacity: 1;}</style><body><div class='description_container'><div class='img_large'><img src='images/AB/Calgary1.png' alt='img1' /><div class='flags'><img src='images/AB/AB.png' alt='flag 1'/><img src='images/AB/Calgary_Flag.png' alt='flag 2'/></div><div class='image_top_text'><h3></h3></div></div><div class='text'><h1>Calgary, AB</h1><p style='color: snow; margin-top: 0px;'>Calgary is the largest city in Alberta. Ranked as the third most livable city in the world in 2022 it contains the most extensive walking and cycling pathway network in North America. Here you can find the Telus Convention Centre, Calgary Tower and, Canada's Olympic and Sports Hall's of Fame.</p><p>You can visit here by using <span class='warp_text' onclick='navigator.clipboard.writeText(this.childNodes[0].textContent)'>/warp Calgary<span class='copy_warp'>Click to copy me</span></span> on the server.</p></div><div class='img_small'><img src='images/AB/Calgary2.png' alt='img2'/><div class='image_bottom_text'></div></div><div class='img_small'><img src='images/AB/Calgary3.png' alt='img3'/><div class='image_bottom_text'>Sunlit Downtown</div></div></div></body></html>","offset":{"x":2,"z":-8}}}},{"type":"icon","data":{"key":"Victoria","point":{"x":-12457677,"z":-7015943},"image":"POI","size":{"x":20.0,"z":20.0},"anchor":{"x":4.5,"z":17.0}},"options":{"stroke":{"weight":5,"color":-13095215},"tooltip":{"content":"Victoria","direction":2,"sticky":true},"popup":{"content":"<html><style>@font-face {font-family: avenir;src: url('fonts/Avenir Regular/Avenir Regular.ttf');}@font-face {font-family: avenir_bold;src: url('fonts/Avenir Heavy/Avenir Heavy.ttf');}.description_container {display: grid;grid-template-columns: auto auto;gap: 10px;padding: 10px;width: 280px;background-image: url('images/Wood.png');background-size: 50px;font-family: avenir;}.img_small {position: relative;height: 75px;}.img_small:hover {transform: scale(1.5);z-index: 1000;}.img_small img {height: 100%;width: 100%;object-fit: cover;}.img_large {position: relative;grid-column: 1 / span 2;height: 150px;object-fit: cover;}.img_large:hover {transform: scale(1.5);z-index: 1000;}.img_large img {height: 100%;width: 100%;object-fit: cover;}.text {grid-column: 1 / span 2;padding: 10px;border-radius: 25px;background-image: url('images/Stone_Bricks.png');background-size: 50px;color: black;}.image_top_text {position: absolute;bottom: -5px;left: 10px;color: snow;font-size: 1.8rem;}.image_bottom_text {position: absolute;bottom: 1px;left: 3px;color: snow;}h1 {font-family: avenir_bold;margin: 0px auto;}.flags {display: flex;position: absolute;top: 5px;left: 3px;padding: 10px;gap: 10px;}.flags img {height: 20px;object-fit: cover;}.warp_text {color: orange;cursor: pointer;position: relative;white-space: nowrap;}.warp_text:hover {color: aqua;text-decoration: underline;}.warp_text .copy_warp {visibility: hidden;width: 120px;background-color: #555;color: #fff;text-align: center;border-radius: 6px;padding: 5px 0;position: absolute;z-index: 1;bottom: 125%;left: 50%;margin-left: -60px;opacity: 0;transition: opacity 0.3s;}.tooltip .tooltiptext::after {content: '';position: absolute;top: 100%;left: 50%;margin-left: -5px;border-width: 5px;border-style: solid;border-color: #555 transparent transparent transparent;}.warp_text:hover .copy_warp {visibility: visible;opacity: 1;}</style><body><div class='description_container'><div class='img_large'><img src='images/BC/Victoria1.png' alt='img1' /><div class='flags'><img src='images/BC/BC.png' alt='flag 1'/><img src='images/BC/Victoria_Flag.png' alt='flag 2'/></div><div class='image_top_text'><h3>Legislative Assembly</h3></div></div><div class='text'><h1>Victoria, BC</h1><p style='color: snow; margin-top: 0px;'>Victoria is the capital of British Columbia. Nicknamed <em>the Garden City</em>, it is famous for the Butchart Gardens, Fairmont Empress hotel and its beautiful coastline. It also contains the oldest China Town in Canada.</p><p>You can visit here by using <span class='warp_text' onclick='navigator.clipboard.writeText(this.childNodes[0].textContent)'>/warp Victoria<span class='copy_warp'>Click to copy me</span></span> on the server.</p></div><div class='img_small'><img src='images/BC/Victoria2.png' alt='img2'/><div class='image_bottom_text'></div></div><div class='img_small'><img src='images/BC/Victoria3.png' alt='img3'/><div class='image_bottom_text'>Empress Hotel</div></div></div></body></html>","offset":{"x":2,"z":-8}}}},{"type":"icon","data":{"key":"Fredericton","point":{"x":-8154464,"z":-6805378},"image":"POI","size":{"x":20.0,"z":20.0},"anchor":{"x":4.5,"z":17.0}},"options":{"stroke":{"weight":5,"color":-13095215},"tooltip":{"content":"Fredericton","direction":2,"sticky":true},"popup":{"content":"<html><style>@font-face {font-family: avenir;src: url('fonts/Avenir Regular/Avenir Regular.ttf');}@font-face {font-family: avenir_bold;src: url('fonts/Avenir Heavy/Avenir Heavy.ttf');}.description_container {display: grid;grid-template-columns: auto auto;gap: 10px;padding: 10px;width: 280px;background-image: url('images/Wood.png');background-size: 50px;font-family: avenir;}.img_small {position: relative;height: 75px;}.img_small:hover {transform: scale(1.5);z-index: 1000;}.img_small img {height: 100%;width: 100%;object-fit: cover;}.img_large {position: relative;grid-column: 1 / span 2;height: 150px;object-fit: cover;}.img_large:hover {transform: scale(1.5);z-index: 1000;}.img_large img {height: 100%;width: 100%;object-fit: cover;}.text {grid-column: 1 / span 2;padding: 10px;border-radius: 25px;background-image: url('images/Stone_Bricks.png');background-size: 50px;color: black;}.image_top_text {position: absolute;bottom: -5px;left: 10px;color: snow;font-size: 1.8rem;}.image_bottom_text {position: absolute;bottom: 1px;left: 3px;color: snow;}h1 {font-family: avenir_bold;margin: 0px auto;}.flags {display: flex;position: absolute;top: 5px;left: 3px;padding: 10px;gap: 10px;}.flags img {height: 20px;object-fit: cover;}.warp_text {color: orange;cursor: pointer;position: relative;white-space: nowrap;}.warp_text:hover {color: aqua;text-decoration: underline;}.warp_text .copy_warp {visibility: hidden;width: 120px;background-color: #555;color: #fff;text-align: center;border-radius: 6px;padding: 5px 0;position: absolute;z-index: 1;bottom: 125%;left: 50%;margin-left: -60px;opacity: 0;transition: opacity 0.3s;}.tooltip .tooltiptext::after {content: '';position: absolute;top: 100%;left: 50%;margin-left: -5px;border-width: 5px;border-style: solid;border-color: #555 transparent transparent transparent;}.warp_text:hover .copy_warp {visibility: visible;opacity: 1;}</style><body><div class='description_container'><div class='img_large'><img src='images/NB/Fredericton1.png' alt='img1' /><div class='flags'><img src='images/NB/NB.png' alt='flag 1'/><img src='images/NB/Fredericton_Flag.png' alt='flag 2'/></div><div class='image_top_text'><h3>Wilmot United Church</h3></div></div><div class='text'><h1>Fredericton, NB</h1><p style='color: snow; margin-top: 0px;'>Fredericton is the capital of New Brunswick. Home of the Harvest Jazz and Blues Festival, the city is steeped in Victorian architecture. You can also find &#8220;Freddy the Nude Dude&#8221;, a historic statue, outside of city hall.</p><p>You can visit here by using <span class='warp_text' onclick='navigator.clipboard.writeText(this.childNodes[0].textContent)'>/warp Fredericton<span class='copy_warp'>Click to copy me</span></span> on the server.</p></div><div class='img_small'><img src='images/NB/Fredericton2.png' alt='img2'/><div class='image_bottom_text'></div></div><div class='img_small'><img src='images/NB/Fredericton3.png' alt='img3'/><div class='image_bottom_text'></div></div></div></body></html>"}}},{"type":"icon","data":{"key":"Quebec","point":{"x":-8524587,"z":-6762599},"image":"POI","size":{"x":20.0,"z":20.0},"anchor":{"x":4.5,"z":17.0}},"options":{"stroke":{"weight":5,"color":-13095215},"tooltip":{"content":"Quebec","direction":2,"sticky":true},"popup":{"content":"<html><style>@font-face {font-family: avenir;src: url('fonts/Avenir Regular/Avenir Regular.ttf');}@font-face {font-family: avenir_bold;src: url('fonts/Avenir Heavy/Avenir Heavy.ttf');}.description_container {display: grid;grid-template-columns: auto auto;gap: 10px;padding: 10px;width: 280px;background-image: url('images/Wood.png');background-size: 50px;font-family: avenir;}.img_small {position: relative;height: 75px;}.img_small:hover {transform: scale(1.5);z-index: 1000;}.img_small img {height: 100%;width: 100%;object-fit: cover;}.img_large {position: relative;grid-column: 1 / span 2;height: 150px;object-fit: cover;}.img_large:hover {transform: scale(1.5);z-index: 1000;}.img_large img {height: 100%;width: 100%;object-fit: cover;}.text {grid-column: 1 / span 2;padding: 10px;border-radius: 25px;background-image: url('images/Stone_Bricks.png');background-size: 50px;color: black;}.image_top_text {position: absolute;bottom: -5px;left: 10px;color: snow;font-size: 1.8rem;}.image_bottom_text {position: absolute;bottom: 1px;left: 3px;color: snow;}h1 {font-family: avenir_bold;margin: 0px auto;}.flags {display: flex;position: absolute;top: 5px;left: 3px;padding: 10px;gap: 10px;}.flags img {height: 20px;object-fit: cover;}.warp_text {color: orange;cursor: pointer;position: relative;white-space: nowrap;}.warp_text:hover {color: aqua;text-decoration: underline;}.warp_text .copy_warp {visibility: hidden;width: 120px;background-color: #555;color: #fff;text-align: center;border-radius: 6px;padding: 5px 0;position: absolute;z-index: 1;bottom: 125%;left: 50%;margin-left: -60px;opacity: 0;transition: opacity 0.3s;}.tooltip .tooltiptext::after {content: '';position: absolute;top: 100%;left: 50%;margin-left: -5px;border-width: 5px;border-style: solid;border-color: #555 transparent transparent transparent;}.warp_text:hover .copy_warp {visibility: visible;opacity: 1;}</style><body><div class='description_container'><div class='img_large'><img src='images/QC/Quebec1.png' alt='img1' /><div class='flags'><img src='images/QC/QC.png' alt='flag 1'/><img src='images/QC/Quebec_Flag.png' alt='flag 2'/></div><div class='image_top_text'><h3></h3></div></div><div class='text'><h1>Québec City, QC</h1><p style='color: snow; margin-top: 0px;'>Québec City is the capital of Québec. (suprised pikachu face) As the only fortified city in Canada, it contains many medieval remnants. Castle walls, cannons and palaces are common sights in the older parts of the city.</p><p>You can visit here by using <span class='warp_text' onclick='navigator.clipboard.writeText(this.childNodes[0].textContent)'> /warp Québec_QC<span class='copy_warp'>Click to copy me</span></span> on the server.</p></div><div class='img_small'><img src='images/QC/Quebec2.png' alt='img2'/><div class='image_bottom_text'></div></div><div class='img_small'><img src='images/QC/Quebec3.png' alt='img3'/><div class='image_bottom_text'></div></div></div></body></html>"}}},{"type":"icon","data":{"key":"Iqaluit","point":{"x":-9043585,"z":-8595501},"image":"POI","size":{"x":20.0,"z":20.0},"anchor":{"x":4.5,"z":17.0}},"options":{"stroke":{"weight":5,"color":-13095215},"tooltip":{"content":"Iqaluit","direction":2,"sticky":true},"popup":{"content":"<html><style>@font-face {font-family: avenir;src: url('fonts/Avenir Regular/Avenir Regular.ttf');}@font-face {font-family: avenir_bold;src: url('fonts/Avenir Heavy/Avenir Heavy.ttf');}.description_container {display: grid;grid-template-columns: auto auto;gap: 10px;padding: 10px;width: 280px;background-image: url('images/Wood.png');background-size: 50px;font-family: avenir;}.img_small {position: relative;height: 75px;}.img_small:hover {transform: scale(1.5);z-index: 1000;}.img_small img {height: 100%;width: 100%;object-fit: cover;}.img_large {position: relative;grid-column: 1 / span 2;height: 150px;object-fit: cover;}.img_large:hover {transform: scale(1.5);z-index: 1000;}.img_large img {height: 100%;width: 100%;object-fit: cover;}.text {grid-column: 1 / span 2;padding: 10px;border-radius: 25px;background-image: url('images/Stone_Bricks.png');background-size: 50px;color: black;}.image_top_text {position: absolute;bottom: -5px;left: 10px;color: snow;font-size: 1.8rem;}.image_bottom_text {position: absolute;bottom: 1px;left: 3px;color: snow;}h1 {font-family: avenir_bold;margin: 0px auto;}.flags {display: flex;position: absolute;top: 5px;left: 3px;padding: 10px;gap: 10px;}.flags img {height: 20px;object-fit: cover;}.warp_text {color: orange;cursor: pointer;position: relative;white-space: nowrap;}.warp_text:hover {color: aqua;text-decoration: underline;}.warp_text .copy_warp {visibility: hidden;width: 120px;background-color: #555;color: #fff;text-align: center;border-radius: 6px;padding: 5px 0;position: absolute;z-index: 1;bottom: 125%;left: 50%;margin-left: -60px;opacity: 0;transition: opacity 0.3s;}.tooltip .tooltiptext::after {content: '';position: absolute;top: 100%;left: 50%;margin-left: -5px;border-width: 5px;border-style: solid;border-color: #555 transparent transparent transparent;}.warp_text:hover .copy_warp {visibility: visible;opacity: 1;}</style><body><div class='description_container'><div class='img_large'><img src='images/NU/Iqaluit1.png' alt='img1' /><div class='flags'><img src='images/NU/NU.png' alt='flag 1'/><img src='images/NU/Iqaluit_Flag.png' alt='flag 2'/></div><div class='image_top_text'><h3></h3></div></div><div class='text'><h1>Iqaluit, NU</h1><p style='color: snow; margin-top: 0px;'>Iqaluit is the capital and only city in Nunavut. It is the northermost city in Canada and enjoys Aurora Borealis year round. Mostly inhabited by Inuits, many buildings incorporate Inuit art designs. St. Jude's Anglican Cathedral is shaped like an igloo, its altar shaped like a sled and the cross is composed of two crossed narwhal tusks.</p><p>You can visit here by using <span class='warp_text' onclick='navigator.clipboard.writeText(this.childNodes[0].textContent)'>/warp Iqaluit<span class='copy_warp'>Click to copy me</span></span> on the server.</p></div><div class='img_small'><img src='images/NU/Iqaluit2.png' alt='img2'/><div class='image_bottom_text'></div></div><div class='img_small'><img src='images/NU/Iqaluit3.png' alt='img3'/><div class='image_bottom_text'></div></div></div></body></html>"}}},{"type":"icon","data":{"key":"Halifax","point":{"x":-7866319,"z":-6773432},"image":"POI","size":{"x":20.0,"z":20.0},"anchor":{"x":4.5,"z":17.0}},"options":{"stroke":{"weight":5,"color":-13095215},"tooltip":{"content":"Halifax","direction":2,"sticky":true},"popup":{"content":"<html><style>@font-face {font-family: avenir;src: url('fonts/Avenir Regular/Avenir Regular.ttf');}@font-face {font-family: avenir_bold;src: url('fonts/Avenir Heavy/Avenir Heavy.ttf');}.description_container {display: grid;grid-template-columns: auto auto;gap: 10px;padding: 10px;width: 280px;background-image: url('images/Wood.png');background-size: 50px;font-family: avenir;}.img_small {position: relative;height: 75px;}.img_small:hover {transform: scale(1.5);z-index: 1000;}.img_small img {height: 100%;width: 100%;object-fit: cover;}.img_large {position: relative;grid-column: 1 / span 2;height: 150px;object-fit: cover;}.img_large:hover {transform: scale(1.5);z-index: 1000;}.img_large img {height: 100%;width: 100%;object-fit: cover;}.text {grid-column: 1 / span 2;padding: 10px;border-radius: 25px;background-image: url('images/Stone_Bricks.png');background-size: 50px;color: black;}.image_top_text {position: absolute;bottom: -5px;left: 10px;color: snow;font-size: 1.8rem;}.image_bottom_text {position: absolute;bottom: 1px;left: 3px;color: snow;}h1 {font-family: avenir_bold;margin: 0px auto;}.flags {display: flex;position: absolute;top: 5px;left: 3px;padding: 10px;gap: 10px;}.flags img {height: 20px;object-fit: cover;}.warp_text {color: orange;cursor: pointer;position: relative;white-space: nowrap;}.warp_text:hover {color: aqua;text-decoration: underline;}.warp_text .copy_warp {visibility: hidden;width: 120px;background-color: #555;color: #fff;text-align: center;border-radius: 6px;padding: 5px 0;position: absolute;z-index: 1;bottom: 125%;left: 50%;margin-left: -60px;opacity: 0;transition: opacity 0.3s;}.tooltip .tooltiptext::after {content: '';position: absolute;top: 100%;left: 50%;margin-left: -5px;border-width: 5px;border-style: solid;border-color: #555 transparent transparent transparent;}.warp_text:hover .copy_warp {visibility: visible;opacity: 1;}</style><body><div class='description_container'><div class='img_large'><img src='images/NS/Halifax1.png' alt='img1' /><div class='flags'><img src='images/NS/NS.png' alt='flag 1'/><img src='images/NS/Halifax_Flag.png' alt='flag 2'/></div><div class='image_top_text'><h3>City Hall</h3></div></div><div class='text'><h1>Halifax, NS</h1><p style='color: snow; margin-top: 0px;'>Halifax is the capital and most populated city of Nova Scotia. It is crested by the Halifax Citadel and known for it's deep non freezing harbour. The Mi'kmaq called the harbour Kjipuktuk (Chebucto) meaning The Great Harbour.</p><p>You can visit here by using <span class='warp_text' onclick='navigator.clipboard.writeText(this.childNodes[0].textContent)'> /warp Halifax<span class='copy_warp'>Click to copy me</span></span> on the server.</p></div><div class='img_small'><img src='images/NS/Halifax2.png' alt='img2'/><div class='image_bottom_text'>The Citadel</div></div><div class='img_small'><img src='images/NS/Halifax3.png' alt='img3'/><div class='image_bottom_text'></div></div></div></body></html>"}}},{"type":"icon","data":{"key":"Winnipeg","point":{"x":-10485141,"z":-6803625},"image":"POI","size":{"x":20.0,"z":20.0},"anchor":{"x":4.5,"z":17.0}},"options":{"stroke":{"weight":5,"color":-13095215},"tooltip":{"content":"Winnipeg","direction":2,"sticky":true},"popup":{"content":"<html><style>@font-face {font-family: avenir;src: url('fonts/Avenir Regular/Avenir Regular.ttf');}@font-face {font-family: avenir_bold;src: url('fonts/Avenir Heavy/Avenir Heavy.ttf');}.description_container {display: grid;grid-template-columns: auto auto;gap: 10px;padding: 10px;width: 280px;background-image: url('images/Wood.png');background-size: 50px;font-family: avenir;}.img_small {position: relative;height: 75px;}.img_small:hover {transform: scale(1.5);z-index: 1000;}.img_small img {height: 100%;width: 100%;object-fit: cover;}.img_large {position: relative;grid-column: 1 / span 2;height: 150px;object-fit: cover;}.img_large:hover {transform: scale(1.5);z-index: 1000;}.img_large img {height: 100%;width: 100%;object-fit: cover;}.text {grid-column: 1 / span 2;padding: 10px;border-radius: 25px;background-image: url('images/Stone_Bricks.png');background-size: 50px;color: black;}.image_top_text {position: absolute;bottom: -5px;left: 10px;color: snow;font-size: 1.8rem;}.image_bottom_text {position: absolute;bottom: 1px;left: 3px;color: snow;}h1 {font-family: avenir_bold;margin: 0px auto;}.flags {display: flex;position: absolute;top: 5px;left: 3px;padding: 10px;gap: 10px;}.flags img {height: 20px;object-fit: cover;}.warp_text {color: orange;cursor: pointer;position: relative;white-space: nowrap;}.warp_text:hover {color: aqua;text-decoration: underline;}.warp_text .copy_warp {visibility: hidden;width: 120px;background-color: #555;color: #fff;text-align: center;border-radius: 6px;padding: 5px 0;position: absolute;z-index: 1;bottom: 125%;left: 50%;margin-left: -60px;opacity: 0;transition: opacity 0.3s;}.tooltip .tooltiptext::after {content: '';position: absolute;top: 100%;left: 50%;margin-left: -5px;border-width: 5px;border-style: solid;border-color: #555 transparent transparent transparent;}.warp_text:hover .copy_warp {visibility: visible;opacity: 1;}</style><body><div class='description_container'><div class='img_large'><img src='images/MB/Winnipeg1.png' alt='img1' /><div class='flags'><img src='images/MB/MB.png' alt='flag 1'/><img src='images/MB/Winnipeg_Flag.png' alt='flag 2'/></div><div class='image_top_text'><h3></h3></div></div><div class='text'><h1>Winnipeg, MB</h1><p style='color: snow; margin-top: 0px;'>Winnipeg is the capital of Manitoba. It contains 26 National Historic Sites within its borders. Structures of interest include the Canadian Museum for Human Rights and The Royal Canadian Mint which produces all of Canada's coinage.</p><p>You can visit here by using <span class='warp_text' onclick='navigator.clipboard.writeText(this.childNodes[0].textContent)'> /warp Winnipeg_MB<span class='copy_warp'>Click to copy me</span></span> on the server.</p></div><div class='img_small'><img src='images/MB/Winnipeg2.png' alt='img2'/><div class='image_bottom_text'></div></div><div class='img_small'><img src='images/MB/Winnipeg3.png' alt='img3'/><div class='image_bottom_text'></div></div></div></body></html>"}}},{"type":"icon","data":{"key":"Edmonton","point":{"x":-11567947,"z":-7374465},"image":"POI","size":{"x":20.0,"z":20.0},"anchor":{"x":4.5,"z":17.0}},"options":{"stroke":{"weight":5,"color":-13095215},"tooltip":{"content":"Edmonton","direction":2,"sticky":true},"popup":{"content":"<html><style>@font-face {font-family: avenir;src: url('fonts/Avenir Regular/Avenir Regular.ttf');}@font-face {font-family: avenir_bold;src: url('fonts/Avenir Heavy/Avenir Heavy.ttf');}.description_container {display: grid;grid-template-columns: auto auto;gap: 10px;padding: 10px;width: 280px;background-image: url('images/Wood.png');background-size: 50px;font-family: avenir;}.img_small {position: relative;height: 75px;}.img_small:hover {transform: scale(1.5);z-index: 1000;}.img_small img {height: 100%;width: 100%;object-fit: cover;}.img_large {position: relative;grid-column: 1 / span 2;height: 150px;object-fit: cover;}.img_large:hover {transform: scale(1.5);z-index: 1000;}.img_large img {height: 100%;width: 100%;object-fit: cover;}.text {grid-column: 1 / span 2;padding: 10px;border-radius: 25px;background-image: url('images/Stone_Bricks.png');background-size: 50px;color: black;}.image_top_text {position: absolute;bottom: -5px;left: 10px;color: snow;font-size: 1.8rem;}.image_bottom_text {position: absolute;bottom: 1px;left: 3px;color: snow;}h1 {font-family: avenir_bold;margin: 0px auto;}.flags {display: flex;position: absolute;top: 5px;left: 3px;padding: 10px;gap: 10px;}.flags img {height: 20px;object-fit: cover;}.warp_text {color: orange;cursor: pointer;position: relative;white-space: nowrap;}.warp_text:hover {color: aqua;text-decoration: underline;}.warp_text .copy_warp {visibility: hidden;width: 120px;background-color: #555;color: #fff;text-align: center;border-radius: 6px;padding: 5px 0;position: absolute;z-index: 1;bottom: 125%;left: 50%;margin-left: -60px;opacity: 0;transition: opacity 0.3s;}.tooltip .tooltiptext::after {content: '';position: absolute;top: 100%;left: 50%;margin-left: -5px;border-width: 5px;border-style: solid;border-color: #555 transparent transparent transparent;}.warp_text:hover .copy_warp {visibility: visible;opacity: 1;}</style><body><div class='description_container'><div class='img_large'><img src='images/AB/Edmonton1.png' alt='img1' /><div class='flags'><img src='images/AB/AB.png' alt='flag 1'/><img src='images/AB/Edmonton_Flag.png' alt='flag 2'/></div><div class='image_top_text'><h3></h3></div></div><div class='text'><h1>Edmonton, AB</h1><p style='color: snow; margin-top: 0px;'>Edmonton is the capital of Alberta. Nicknamed the oil capital of Canada, it is our largest fossil fuel export hub. Here you will find North America's largest mall (the world's largest from 1981 to 2004) and the Rogers Place Arena.</p><p>You can visit here by using <span class='warp_text' onclick='navigator.clipboard.writeText(this.childNodes[0].textContent)'>/warp Edmonton<span class='copy_warp'>Click to copy me</span></span> on the server.</p></div><div class='img_small'><img src='images/AB/Edmonton2.png' alt='img2'/><div class='image_bottom_text'>Royal Alberta Museum</div></div><div class='img_small'><img src='images/AB/Edmonton3.png' alt='img3'/><div class='image_bottom_text'></div></div></div></body></html>"}}},{"type":"icon","data":{"key":"Niagara Falls","point":{"x":-9018351,"z":-6177423},"image":"pin","size":{"x":20.0,"z":20.0},"anchor":{"x":8.0,"z":17.0}},"options":{"stroke":{"weight":5,"color":-13095215},"tooltip":{"content":"Niagara Falls","direction":2,"sticky":true},"popup":{"content":"<html><style>@font-face {font-family: avenir;src: url('fonts/Avenir Regular/Avenir Regular.ttf');}@font-face {font-family: avenir_bold;src: url('fonts/Avenir Heavy/Avenir Heavy.ttf');}.description_container {display: grid;grid-template-columns: auto auto;gap: 10px;padding: 10px;width: 280px;background-image: url('images/Wood.png');background-size: 50px;font-family: avenir;}.img_small {position: relative;height: 75px;}.img_small:hover {transform: scale(1.5);z-index: 1000;}.img_small img {height: 100%;width: 100%;object-fit: cover;}.img_large {position: relative;grid-column: 1 / span 2;height: 150px;object-fit: cover;}.img_large:hover {transform: scale(1.5);z-index: 1000;}.img_large img {height: 100%;width: 100%;object-fit: cover;}.text {grid-column: 1 / span 2;padding: 10px;border-radius: 25px;background-image: url('images/Stone_Bricks.png');background-size: 50px;color: black;}.image_top_text {position: absolute;bottom: -5px;left: 10px;color: snow;font-size: 1.8rem;}.image_bottom_text {position: absolute;bottom: 1px;left: 3px;color: snow;}h1 {font-family: avenir_bold;margin: 0px auto;}.flags {display: flex;position: absolute;top: 5px;left: 3px;padding: 10px;gap: 10px;}.flags img {height: 20px;object-fit: cover;}.warp_text {color: orange;cursor: pointer;position: relative;white-space: nowrap;}.warp_text:hover {color: aqua;text-decoration: underline;}.warp_text .copy_warp {visibility: hidden;width: 120px;background-color: #555;color: #fff;text-align: center;border-radius: 6px;padding: 5px 0;position: absolute;z-index: 1;bottom: 125%;left: 50%;margin-left: -60px;opacity: 0;transition: opacity 0.3s;}.tooltip .tooltiptext::after {content: '';position: absolute;top: 100%;left: 50%;margin-left: -5px;border-width: 5px;border-style: solid;border-color: #555 transparent transparent transparent;}.warp_text:hover .copy_warp {visibility: visible;opacity: 1;}</style><body><div class='description_container'><div class='img_large'><img src='images/ON/NiagaraFalls1.png' alt='img1' /><div class='flags'><img src='images/ON/ON.png' alt='flag 1'/></div><div class='image_top_text'><h3></h3></div></div><div class='text'><h1>Niagara Falls, ON</h1><p style='color: snow; margin-top: 0px;'>Niagara Falls is composed of three waterfalls on the border of Ontario and New York. These falls have the highest flow rate of any waterfall in North America. They are also known for the terrifying practice of barrel jumping, tumbling over the falls while inside a barrel, with mixed results. </p><p>You can visit here by using <span class='warp_text' onclick='navigator.clipboard.writeText(this.childNodes[0].textContent)'>/warp Niagara_Falls<span class='copy_warp'>Click to copy me</span><span class='copy_warp'>Click to copy me</span></span> on the server.</p></div><div class='img_small'><img src='images/ON/NiagaraFalls2.png' alt='img2'/><div class='image_bottom_text'></div></div><div class='img_small'><img src='images/ON/NiagaraFalls3.png' alt='img3'/><div class='image_bottom_text'></div></div></div></body></html>","offset":{"x":2,"z":-8}}}},{"type":"icon","data":{"key":"Trial_Area","point":{"x":-9073902,"z":-6241184},"image":"pin","size":{"x":20.0,"z":20.0},"anchor":{"x":4.5,"z":17.0}},"options":{"stroke":{"weight":5,"color":-13095215},"tooltip":{"content":"Trial Area","direction":2,"sticky":true},"popup":{"content":"<html><style>@font-face {font-family: avenir;src: url('fonts/Avenir Regular/Avenir Regular.ttf');}@font-face {font-family: avenir_bold;src: url('fonts/Avenir Heavy/Avenir Heavy.ttf');}.description_container {display: grid;grid-template-columns: auto auto;gap: 10px;padding: 10px;width: 280px;background-image: url('images/Wood.png');background-size: 50px;font-family: avenir;}.img_small {position: relative;height: 75px;}.img_small:hover {transform: scale(1.5);z-index: 1000;}.img_small img {height: 100%;width: 100%;object-fit: cover;}.img_large {position: relative;grid-column: 1 / span 2;height: 150px;object-fit: cover;}.img_large:hover {transform: scale(1.5);z-index: 1000;}.img_large img {height: 100%;width: 100%;object-fit: cover;}.text {grid-column: 1 / span 2;padding: 10px;border-radius: 25px;background-image: url('images/Stone_Bricks.png');background-size: 50px;color: black;}.image_top_text {position: absolute;bottom: -5px;left: 10px;color: snow;font-size: 1.8rem;}.image_bottom_text {position: absolute;bottom: 1px;left: 3px;color: snow;}h1 {font-family: avenir_bold;margin: 0px auto;}.flags {display: flex;position: absolute;top: 5px;left: 3px;padding: 10px;gap: 10px;}.flags img {height: 20px;object-fit: cover;}.warp_text {color: orange;cursor: pointer;position: relative;white-space: nowrap;}.warp_text:hover {color: aqua;text-decoration: underline;}.warp_text .copy_warp {visibility: hidden;width: 120px;background-color: #555;color: #fff;text-align: center;border-radius: 6px;padding: 5px 0;position: absolute;z-index: 1;bottom: 125%;left: 50%;margin-left: -60px;opacity: 0;transition: opacity 0.3s;}.tooltip .tooltiptext::after {content: '';position: absolute;top: 100%;left: 50%;margin-left: -5px;border-width: 5px;border-style: solid;border-color: #555 transparent transparent transparent;}.warp_text:hover .copy_warp {visibility: visible;opacity: 1;}</style><body><div class='description_container'><div class='img_large'><img src='images/Trial_Area/Trial1.png' alt='img1' /><!--<div class='flags'><img src='images/Trial_Area/BTECanada.png' alt='flag 1'/></div>--><div class='image_top_text'><h3></h3></div></div><div class='text'><h1>Trial Area</h1><p style='color: snow; margin-top: 0px;'>Where every potential builder begins, the Trial Area is a practice grounds for those interested in becoming a builder. Here, you will build your first house by following the provided tutorial. Visit the <a style='color: orange;' href='https://discord.gg/Q9EH8GB4'><b>#Become-a-Builder</b></a> channel in the discord to find more information.</p><p>You can visit here by using <span class='warp_text' onclick='navigator.clipboard.writeText(this.childNodes[0].textContent)'>/trial<span class='copy_warp'>Click to copy me</span></span> on the server.</p></div><div class='img_small'><img src='images/Trial_Area/Trial2.png' alt='img2'/><div class='image_bottom_text'></div></div><div class='img_small'><img src='images/Trial_Area/Trial3.png' alt='img3'/><div class='image_bottom_text'></div></div></div></body></html>"}}},{"type":"icon","data":{"key":"Ottawa","point":{"x":-8814837,"z":-6504824},"image":"POI","size":{"x":20.0,"z":20.0},"anchor":{"x":4.5,"z":17.0}},"options":{"stroke":{"weight":5,"color":-13095215},"tooltip":{"content":"Ottawa","direction":2,"sticky":true},"popup":{"content":"<html><style>@font-face {font-family: avenir;src: url('fonts/Avenir Regular/Avenir Regular.ttf');}@font-face {font-family: avenir_bold;src: url('fonts/Avenir Heavy/Avenir Heavy.ttf');}.description_container {display: grid;grid-template-columns: auto auto;gap: 10px;padding: 10px;width: 280px;background-image: url('images/Wood.png');background-size: 50px;font-family: avenir;}.img_small {position: relative;height: 75px;}.img_small:hover {transform: scale(1.5);z-index: 1000;}.img_small img {height: 100%;width: 100%;object-fit: cover;}.img_large {position: relative;grid-column: 1 / span 2;height: 150px;object-fit: cover;}.img_large:hover {transform: scale(1.5);z-index: 1000;}.img_large img {height: 100%;width: 100%;object-fit: cover;}.text {grid-column: 1 / span 2;padding: 10px;border-radius: 25px;background-image: url('images/Stone_Bricks.png');background-size: 50px;color: black;}.image_top_text {position: absolute;bottom: -5px;left: 10px;color: snow;font-size: 1.8rem;}.image_bottom_text {position: absolute;bottom: 1px;left: 3px;color: snow;}h1 {font-family: avenir_bold;margin: 0px auto;}.flags {display: flex;position: absolute;top: 5px;left: 3px;padding: 10px;gap: 10px;}.flags img {height: 20px;object-fit: cover;}.warp_text {color: orange;cursor: pointer;position: relative;white-space: nowrap;}.warp_text:hover {color: aqua;text-decoration: underline;}.warp_text .copy_warp {visibility: hidden;width: 120px;background-color: #555;color: #fff;text-align: center;border-radius: 6px;padding: 5px 0;position: absolute;z-index: 1;bottom: 125%;left: 50%;margin-left: -60px;opacity: 0;transition: opacity 0.3s;}.tooltip .tooltiptext::after {content: '';position: absolute;top: 100%;left: 50%;margin-left: -5px;border-width: 5px;border-style: solid;border-color: #555 transparent transparent transparent;}.warp_text:hover .copy_warp {visibility: visible;opacity: 1;}</style><body><div class='description_container'><div class='img_large'><img src='images/ON/Ottawa1.png' alt='img1' /><div class='flags'><img src='images/ON/ON.png' alt='flag 1'/><img src='images/oN/Ottawa_Flag.png' alt='flag 2'/></div><div class='image_top_text'><h3>Parliament</h3></div></div><div class='text'><h1>Ottawa, ON</h1><p style='color: snow; margin-top: 0px;'>Ottawa is the capital city of Canada, located in Ontario at the confluence of the Ottawa and Rideau Rivers. It is known for its rich history, bilingual culture, and significant government buildings, including Parliament Hill and various national museums.</p><p>You can visit here by using <span class='warp_text' onclick='navigator.clipboard.writeText(this.childNodes[0].textContent)'>/warp Ottawa<span class='copy_warp'>Click to copy me</span></span> on the server.</p></div><div class='img_small'><img src='images/ON/Ottawa2.png' alt='img2'/><div class='image_bottom_text'></div></div><div class='img_small'><img src='images/ON/Ottawa3.png' alt='img3'/><div class='image_bottom_text'>National War Memorial</div></div></div></body></html>"}}},{"type":"icon","data":{"key":"Saint John's","point":{"x":-7302283,"z":-7499282},"image":"POI","size":{"x":20.0,"z":20.0},"anchor":{"x":4.5,"z":17.0}},"options":{"stroke":{"weight":5,"color":-13095215},"tooltip":{"content":"Saint John&sup2","direction":2,"sticky":true},"popup":{"content":"<html><style>@font-face {font-family: avenir;src: url('fonts/Avenir Regular/Avenir Regular.ttf');}@font-face {font-family: avenir_bold;src: url('fonts/Avenir Heavy/Avenir Heavy.ttf');}.description_container {display: grid;grid-template-columns: auto auto;gap: 10px;padding: 10px;width: 280px;background-image: url('images/Wood.png');background-size: 50px;font-family: avenir;}.img_small {position: relative;height: 75px;}.img_small:hover {transform: scale(1.5);z-index: 1000;}.img_small img {height: 100%;width: 100%;object-fit: cover;}.img_large {position: relative;grid-column: 1 / span 2;height: 150px;object-fit: cover;}.img_large:hover {transform: scale(1.5);z-index: 1000;}.img_large img {height: 100%;width: 100%;object-fit: cover;}.text {grid-column: 1 / span 2;padding: 10px;border-radius: 25px;background-image: url('images/Stone_Bricks.png');background-size: 50px;color: black;}.image_top_text {position: absolute;bottom: -5px;left: 10px;color: snow;font-size: 1.8rem;}.image_bottom_text {position: absolute;bottom: 1px;left: 3px;color: snow;}h1 {font-family: avenir_bold;margin: 0px auto;}.flags {display: flex;position: absolute;top: 5px;left: 3px;padding: 10px;gap: 10px;}.flags img {height: 20px;object-fit: cover;}.warp_text {color: orange;cursor: pointer;position: relative;white-space: nowrap;}.warp_text:hover {color: aqua;text-decoration: underline;}.warp_text .copy_warp {visibility: hidden;width: 120px;background-color: #555;color: #fff;text-align: center;border-radius: 6px;padding: 5px 0;position: absolute;z-index: 1;bottom: 125%;left: 50%;margin-left: -60px;opacity: 0;transition: opacity 0.3s;}.tooltip .tooltiptext::after {content: '';position: absolute;top: 100%;left: 50%;margin-left: -5px;border-width: 5px;border-style: solid;border-color: #555 transparent transparent transparent;}.warp_text:hover .copy_warp {visibility: visible;opacity: 1;}</style><body><div class='description_container'><div class='img_large'><img src='images/NL/StJohns1.png' alt='img1' /><div class='flags'><img src='images/NL/NL.png' alt='flag 1'/><img src='images/NL/StJohns_Flag.png' alt='flag 2'/></div><div class='image_top_text'><h3></h3></div></div><div class='text'><h1>St John's, NL</h1><p style='color: snow; margin-top: 0px;'>St John's is the capital of Newfoundland and Labrador. Sitting on the easternmost point of Canada, it was a common landing spot for ships traversing the ocean. This led to a tumultuous history as nations waged war to claim it. Downtown is mainly composed of historic fishermen homes, sheds and storage turned into housing. It earned the name <em>Jelly Bean Row</em> for its colorful tightly packed homes.</p><p>You can visit here by using <span class='warp_text' onclick='navigator.clipboard.writeText(this.childNodes[0].textContent)'>/warp StJohns<span class='copy_warp'>Click to copy me</span></span> on the server.</p></div><div class='img_small'><img src='images/NL/StJohns2.png' alt='img2'/><div class='image_bottom_text'></div></div><div class='img_small'><img src='images/NL/StJohns3.png' alt='img3'/><div class='image_bottom_text'></div></div></div></body></html>"}}},{"type":"icon","data":{"key":"Montreal","point":{"x":-8653658,"z":-6561537},"image":"pin","size":{"x":20.0,"z":20.0},"anchor":{"x":4.5,"z":17.0}},"options":{"stroke":{"weight":5,"color":-13095215},"tooltip":{"content":"Montreal","direction":2,"sticky":true},"popup":{"content":"<html><style>@font-face {font-family: avenir;src: url('fonts/Avenir Regular/Avenir Regular.ttf');}@font-face {font-family: avenir_bold;src: url('fonts/Avenir Heavy/Avenir Heavy.ttf');}.description_container {display: grid;grid-template-columns: auto auto;gap: 10px;padding: 10px;width: 280px;background-image: url('images/Wood.png');background-size: 50px;font-family: avenir;}.img_small {position: relative;height: 75px;}.img_small:hover {transform: scale(1.5);z-index: 1000;}.img_small img {height: 100%;width: 100%;object-fit: cover;}.img_large {position: relative;grid-column: 1 / span 2;height: 150px;object-fit: cover;}.img_large:hover {transform: scale(1.5);z-index: 1000;}.img_large img {height: 100%;width: 100%;object-fit: cover;}.text {grid-column: 1 / span 2;padding: 10px;border-radius: 25px;background-image: url('images/Stone_Bricks.png');background-size: 50px;color: black;}.image_top_text {position: absolute;bottom: -5px;left: 10px;color: snow;font-size: 1.8rem;}.image_bottom_text {position: absolute;bottom: 1px;left: 3px;color: snow;}h1 {font-family: avenir_bold;margin: 0px auto;}.flags {display: flex;position: absolute;top: 5px;left: 3px;padding: 10px;gap: 10px;}.flags img {height: 20px;object-fit: cover;}.warp_text {color: orange;cursor: pointer;position: relative;white-space: nowrap;}.warp_text:hover {color: aqua;text-decoration: underline;}.warp_text .copy_warp {visibility: hidden;width: 120px;background-color: #555;color: #fff;text-align: center;border-radius: 6px;padding: 5px 0;position: absolute;z-index: 1;bottom: 125%;left: 50%;margin-left: -60px;opacity: 0;transition: opacity 0.3s;}.tooltip .tooltiptext::after {content: '';position: absolute;top: 100%;left: 50%;margin-left: -5px;border-width: 5px;border-style: solid;border-color: #555 transparent transparent transparent;}.warp_text:hover .copy_warp {visibility: visible;opacity: 1;}</style><body><div class='description_container'><div class='img_large'><img src='images/QC/Montreal1.png' alt='img1' /><div class='flags'><img src='images/QC/QC.png' alt='flag 1'/><img src='images/QC/Montreal_Flag.png' alt='flag 2'/></div><div class='image_top_text'><h3></h3></div></div><div class='text'><h1>Montréal, QC</h1><p style='color: snow; margin-top: 0px;'>Montréal is the largest city in Québec, Canada, known for its rich history, vibrant culture, and diverse population. It features a unique blend of European and North American influences, with attractions like Old Montréal, Mount Royal, and a lively arts scene</p><p>You can visit here by using <span class='warp_text' onclick='navigator.clipboard.writeText(this.childNodes[0].textContent)'>/warp Montréal<span class='copy_warp'>Click to copy me</span></span> on the server.</p></div><div class='img_small'><img src='images/QC/Montreal2.png' alt='img2'/><div class='image_bottom_text'></div></div><div class='img_small'><img src='images/QC/Montreal3.png' alt='img3'/><div class='image_bottom_text'></div></div></div></body></html>"}}},{"type":"icon","data":{"key":"Toronto","point":{"x":-9057004,"z":-6235317},"image":"POI","size":{"x":20.0,"z":20.0},"anchor":{"x":4.5,"z":17.0}},"options":{"stroke":{"weight":5,"color":-13095215},"tooltip":{"content":"Toronto","direction":2,"sticky":true},"popup":{"content":"<html><style>@font-face {font-family: avenir;src: url('fonts/Avenir Regular/Avenir Regular.ttf');}@font-face {font-family: avenir_bold;src: url('fonts/Avenir Heavy/Avenir Heavy.ttf');}.description_container {display: grid;grid-template-columns: auto auto;gap: 10px;padding: 10px;width: 280px;background-image: url('images/Wood.png');background-size: 50px;font-family: avenir;}.img_small {position: relative;height: 75px;}.img_small:hover {transform: scale(1.5);z-index: 1000;}.img_small img {height: 100%;width: 100%;object-fit: cover;}.img_large {position: relative;grid-column: 1 / span 2;height: 150px;object-fit: cover;}.img_large:hover {transform: scale(1.5);z-index: 1000;}.img_large img {height: 100%;width: 100%;object-fit: cover;}.text {grid-column: 1 / span 2;padding: 10px;border-radius: 25px;background-image: url('images/Stone_Bricks.png');background-size: 50px;color: black;}.image_top_text {position: absolute;bottom: -5px;left: 10px;color: snow;font-size: 1.8rem;}.image_bottom_text {position: absolute;bottom: 1px;left: 3px;color: snow;}h1 {font-family: avenir_bold;margin: 0px auto;}.flags {display: flex;position: absolute;top: 5px;left: 3px;padding: 10px;gap: 10px;}.flags img {height: 20px;object-fit: cover;}.warp_text {color: orange;cursor: pointer;position: relative;white-space: nowrap;}.warp_text:hover {color: aqua;text-decoration: underline;}.warp_text .copy_warp {visibility: hidden;width: 120px;background-color: #555;color: #fff;text-align: center;border-radius: 6px;padding: 5px 0;position: absolute;z-index: 1;bottom: 125%;left: 50%;margin-left: -60px;opacity: 0;transition: opacity 0.3s;}.tooltip .tooltiptext::after {content: '';position: absolute;top: 100%;left: 50%;margin-left: -5px;border-width: 5px;border-style: solid;border-color: #555 transparent transparent transparent;}.warp_text:hover .copy_warp {visibility: visible;opacity: 1;}</style><body><div class='description_container'><div class='img_large'><img src='images/ON/Toronto1.png' alt='img1' /><div class='flags'><img src='images/ON/ON.png' alt='flag 1'/><img src='images/ON/Toronto_Flag.png' alt='flag 2'/></div><div class='image_top_text'><h3></h3></div></div><div class='text'><h1>Toronto, ON</h1><p style='color: snow; margin-top: 0px;'>Toronto is the capital of Ontario. A vibrant city, it features prominent music, theatre and television productions. Additinally, it is the site of the tallest freestanding structure in North America, the CN Tower.</p><p>You can visit here by using <span class='warp_text' onclick='navigator.clipboard.writeText(this.childNodes[0].textContent)'>/warp Toronto<span class='copy_warp'>Click to copy me</span></span> on the server.</p></div><div class='img_small'><img src='images/ON/Toronto2.png' alt='img2'/><div class='image_bottom_text'></div></div><div class='img_small'><img src='images/ON/Toronto3.png' alt='img3'/><div class='image_bottom_text'></div></div></div></body></html>"}}}]